collective.faceted.taxonomywidget-1.0a4-py2.7-nspkg.pth
collective/faceted/taxonomywidget/__init__.py
collective/faceted/taxonomywidget/configure.zcml
collective/faceted/taxonomywidget/browser/__init__.py
collective/faceted/taxonomywidget/browser/configure.zcml
collective/faceted/taxonomywidget/browser/select_widget.pt
collective/faceted/taxonomywidget/browser/widget.py
collective/faceted/taxonomywidget/browser/static/.gitkeep
collective/faceted/taxonomywidget/browser/static/select2_edit.js
collective/faceted/taxonomywidget/browser/static/select2_view.css
collective/faceted/taxonomywidget/browser/static/select2_view.js
collective/faceted/taxonomywidget/browser/static/select_edit.js
collective/faceted/taxonomywidget/browser/static/select_view.css
collective/faceted/taxonomywidget/browser/static/select_view.js
collective/faceted/taxonomywidget/locales/collective.faceted.taxonomywidget.pot
collective/faceted/taxonomywidget/locales/update.sh
collective/faceted/taxonomywidget/locales/fr/LC_MESSAGES/collective.faceted.taxonomywidget.po
collective/faceted/taxonomywidget/profiles/default/collectivefacetedtaxonomywidget_default.txt
collective/faceted/taxonomywidget/profiles/default/metadata.xml
collective.faceted.taxonomywidget-1.0a4.dist-info/DESCRIPTION.rst
collective.faceted.taxonomywidget-1.0a4.dist-info/METADATA
collective.faceted.taxonomywidget-1.0a4.dist-info/RECORD
collective.faceted.taxonomywidget-1.0a4.dist-info/WHEEL
collective.faceted.taxonomywidget-1.0a4.dist-info/entry_points.txt
collective.faceted.taxonomywidget-1.0a4.dist-info/metadata.json
collective.faceted.taxonomywidget-1.0a4.dist-info/namespace_packages.txt
collective.faceted.taxonomywidget-1.0a4.dist-info/top_level.txt
